{
  "profile": {
    "name": "Kelurahan Kemayoran",
    "kecamatan": "Krembangan",
    "kota": "Surabaya",
    "provinsi": "Jawa Timur",
    "kodePos": "60177",
    "luasWilayah": "2.35",
    "jumlahPenduduk": 17659,
    "kepadatan": 7514,
    "batasWilayah": {
      "utara": "Kelurahan Kemayoran Barat",
      "selatan": "Kelurahan Perak Utara",
      "timur": "Kelurahan Krembangan Utara",
      "barat": "Kali Mas"
    },
    "visi": "Terwujudnya Kelurahan Kemayoran sebagai wilayah yang maju, mandiri, dan sejahtera dengan pelayanan prima berbasis teknologi.",
    "misi": [
      "Meningkatkan kualitas pelayanan publik yang prima dan transparan",
      "Memberdayakan masyarakat melalui program-program pembangunan berkelanjutan",
      "Mengembangkan ekonomi kerakyatan dan UMKM lokal",
      "Memperkuat sistem keamanan dan ketertiban masyarakat",
      "Membangun infrastruktur yang mendukung kesejahteraan warga"
    ]
  },
  "aparatur": [
    {
      "id": 1,
      "nama": "Saefuddin Zuhri S.Kep.Ns, M.Kes",
      "jabatan": "Lurah"
    },
    {
      "id": 2,
      "nama": "Suro Dewati S.T.",
      "jabatan": "Sekretaris Kelurahan"
    },
    {
      "id": 3,
      "nama": "Rindara Rudiyati S.Pd",
      "jabatan": "Seksi Pemerintahan dan Pelayanan Publik"
    },
    {
      "id": 4,
      "nama": "Heri Susilo, S.ST.Kesling",
      "jabatan": "Seksi Kesejahteraan Rakyat dan Perekonomian"
    },
    {
      "id": 5,
      "nama": "Djiantono SH",
      "jabatan": "Seksi Ketentraman Ketertiban dan Pembangunan"
    }
  ]
}
